{"@level":"info","@message":"Terraform 1.1.3","@module":"terraform.ui","@timestamp":"2022-05-03T23:06:48.457547+02:00","terraform":"1.1.3","type":"version","ui":"1.0"}
{"@level":"error","@message":"Error: Invalid expression","@module":"terraform.ui","@timestamp":"2022-05-03T23:06:48.461541+02:00","diagnostic":{"severity":"error","summary":"Invalid expression","detail":"Expected the start of an expression, but found an invalid expression token.","range":{"filename":"main.tf","start":{"line":142,"column":18,"byte":2525},"end":{"line":143,"column":1,"byte":2527}},"snippet":{"context":"resource \"aws_security_group\" \"name_0\"","code":"    to_port     =\n}","start_line":142,"highlight_start_offset":17,"highlight_end_offset":19,"values":[]}},"type":"diagnostic"}
