{"@level":"info","@message":"Terraform 1.1.7","@module":"terraform.ui","@timestamp":"2022-04-30T20:53:46.616637+02:00","terraform":"1.1.7","type":"version","ui":"1.0"}
{"@level":"error","@message":"Error: Argument or block definition required","@module":"terraform.ui","@timestamp":"2022-04-30T20:53:46.619249+02:00","diagnostic":{"severity":"error","summary":"Argument or block definition required","detail":"An argument or block definition is required here. To set an argument, use the equals sign \"=\" to introduce the argument value.","range":{"filename":"main.tf","start":{"line":1,"column":1,"byte":0},"end":{"line":1,"column":9,"byte":8}},"snippet":{"context":null,"code":"provider","start_line":1,"highlight_start_offset":0,"highlight_end_offset":8,"values":[]}},"type":"diagnostic"}
{"@level":"error","@message":"Error: Attribute redefined","@module":"terraform.ui","@timestamp":"2022-04-30T20:53:46.620866+02:00","diagnostic":{"severity":"error","summary":"Attribute redefined","detail":"The argument \"Environment\" was already set at main.tf:23,5-16. Each argument may be set only once.","range":{"filename":"main.tf","start":{"line":28,"column":5,"byte":601},"end":{"line":28,"column":16,"byte":612}},"snippet":{"context":"resource \"aws_s3_bucket\" \"name_0\"","code":"    Environment = var.environment","start_line":28,"highlight_start_offset":4,"highlight_end_offset":15,"values":[]}},"type":"diagnostic"}
{"@level":"error","@message":"Error: Attribute redefined","@module":"terraform.ui","@timestamp":"2022-04-30T20:53:46.621381+02:00","diagnostic":{"severity":"error","summary":"Attribute redefined","detail":"The argument \"Environment\" was already set at main.tf:39,5-16. Each argument may be set only once.","range":{"filename":"main.tf","start":{"line":44,"column":5,"byte":1022},"end":{"line":44,"column":16,"byte":1033}},"snippet":{"context":"resource \"aws_s3_bucket\" \"name_1\"","code":"    Environment = var.environment","start_line":44,"highlight_start_offset":4,"highlight_end_offset":15,"values":[]}},"type":"diagnostic"}
