{"@level":"info","@message":"Terraform 1.1.7","@module":"terraform.ui","@timestamp":"2022-05-05T09:37:05.587366+02:00","terraform":"1.1.7","type":"version","ui":"1.0"}
{"@level":"error","@message":"Error: Invalid reference","@module":"terraform.ui","@timestamp":"2022-05-05T09:37:07.088796+02:00","diagnostic":{"severity":"error","summary":"Invalid reference","detail":"A reference to a resource type must be followed by at least one attribute access, specifying the resource name.","range":{"filename":"main.tf","start":{"line":15,"column":32,"byte":260},"end":{"line":15,"column":45,"byte":273}},"snippet":{"context":"resource \"google_compute_network\" \"name_0\"","code":"  name = \"my-compute-network-${random_suffix}\"","start_line":15,"highlight_start_offset":31,"highlight_end_offset":44,"values":[]}},"type":"diagnostic"}
{"@level":"error","@message":"Error: Invalid reference","@module":"terraform.ui","@timestamp":"2022-05-05T09:37:07.089306+02:00","diagnostic":{"severity":"error","summary":"Invalid reference","detail":"A reference to a resource type must be followed by at least one attribute access, specifying the resource name.","range":{"filename":"main.tf","start":{"line":26,"column":32,"byte":573},"end":{"line":26,"column":45,"byte":586}},"snippet":{"context":"resource \"google_compute_address\" \"name_2\"","code":"  name = \"my-compute-address-${random_suffix}\"","start_line":26,"highlight_start_offset":31,"highlight_end_offset":44,"values":[]}},"type":"diagnostic"}
{"@level":"error","@message":"Error: Invalid reference","@module":"terraform.ui","@timestamp":"2022-05-05T09:37:07.089306+02:00","diagnostic":{"severity":"error","summary":"Invalid reference","detail":"A reference to a resource type must be followed by at least one attribute access, specifying the resource name.","range":{"filename":"main.tf","start":{"line":20,"column":44,"byte":404},"end":{"line":20,"column":57,"byte":417}},"snippet":{"context":"resource \"google_compute_subnetwork\" \"name_1\"","code":"  name          = \"my-compute-subnetwork-${random_suffix}\"","start_line":20,"highlight_start_offset":43,"highlight_end_offset":56,"values":[]}},"type":"diagnostic"}
